tamagotchi/__init__.py
tamagotchi/__main__.py
tamagotchi/input_image.png
tamagotchi/tama-1.txt
tamagotchi/tama-10.txt
tamagotchi/tama-11.txt
tamagotchi/tama-2.txt
tamagotchi/tama-3.txt
tamagotchi/tama-4.txt
tamagotchi/tama-5.txt
tamagotchi/tama-6.txt
tamagotchi/tama-7.txt
tamagotchi/tama-8.txt
tamagotchi/tama-9.txt
tamagotchi/tamagotchi.py
tamagotchi-0.1.2.dist-info/LICENSE
tamagotchi-0.1.2.dist-info/METADATA
tamagotchi-0.1.2.dist-info/WHEEL
tamagotchi-0.1.2.dist-info/entry_points.txt
tamagotchi-0.1.2.dist-info/top_level.txt
tamagotchi-0.1.2.dist-info/RECORD
