Metadata-Version: 2.1
Name: tamagotchi
Version: 0.1.2
Summary: Create and interact with your very own Tamagotchi character using Python! \(^ 3 ^)/
Author-email: Sahar Bueno-Abdala <sb8249@nyu.edu>, Hang Yin <hy2270@nyu.edu>, Jessica Xu <kx2053@nyu.edu>
License: MIT License
Project-URL: Homepage, https://github.com/software-students-fall2024/3-python-package-macaron-for-three
Project-URL: Repository, https://github.com/software-students-fall2024/3-python-package-macaron-for-three.git
Project-URL: BugTracker, https://github.com/software-students-fall2024/3-python-package-macaron-for-three/issues
Keywords: python,package,build,tutorial
Classifier: Environment :: Console
Classifier: Intended Audience :: Developers
Classifier: License :: OSI Approved :: MIT License
Classifier: Natural Language :: English
Classifier: Operating System :: OS Independent
Classifier: Programming Language :: Python :: 3.7
Classifier: Programming Language :: Python :: 3.8
Classifier: Programming Language :: Python :: 3.9
Classifier: Programming Language :: Python :: 3.10
Classifier: Programming Language :: Python :: 3.11
Classifier: Programming Language :: Python :: 3.12
Classifier: Topic :: Communications :: Chat
Classifier: Topic :: Games/Entertainment
Classifier: Topic :: Software Development :: Libraries :: Python Modules
Requires-Python: >=3.7
License-File: LICENSE
Requires-Dist: numpy
Requires-Dist: Pillow
Provides-Extra: dev
Requires-Dist: pytest; extra == "dev"
